npm_mcp/__init__.py
npm_mcp/__main__.py
npm_mcp/constants.py
npm_mcp/instance_manager.py
npm_mcp/py.typed
npm_mcp/server.py
npm_mcp/types.py
npm_mcp/auth/__init__.py
npm_mcp/auth/manager.py
npm_mcp/auth/token_cache.py
npm_mcp/client/__init__.py
npm_mcp/client/http_client.py
npm_mcp/client/npm_client.py
npm_mcp/config/__init__.py
npm_mcp/config/encryption.py
npm_mcp/config/loader.py
npm_mcp/config/models.py
npm_mcp/models/__init__.py
npm_mcp/models/access_list.py
npm_mcp/models/bulk.py
npm_mcp/models/certificate.py
npm_mcp/models/dead_host.py
npm_mcp/models/proxy_host.py
npm_mcp/models/redirection.py
npm_mcp/models/settings.py
npm_mcp/models/stream.py
npm_mcp/models/user.py
npm_mcp/prompts/__init__.py
npm_mcp/prompts/bulk_operations.py
npm_mcp/prompts/certificate_management.py
npm_mcp/prompts/proxy_setup.py
npm_mcp/prompts/security_review.py
npm_mcp/tools/__init__.py
npm_mcp/tools/access_list.py
npm_mcp/tools/bulk.py
npm_mcp/tools/categories.py
npm_mcp/tools/certificate.py
npm_mcp/tools/compact.py
npm_mcp/tools/instance.py
npm_mcp/tools/proxy_host.py
npm_mcp/tools/redirection.py
npm_mcp/tools/stream.py
npm_mcp/tools/system.py
npm_mcp/tools/user.py
npm_mcp/utils/__init__.py
npm_mcp/utils/batch.py
npm_mcp/utils/logging.py
npm_mcp-1.0.0.dist-info/licenses/LICENSE
npm_mcp-1.0.0.dist-info/METADATA
npm_mcp-1.0.0.dist-info/WHEEL
npm_mcp-1.0.0.dist-info/entry_points.txt
npm_mcp-1.0.0.dist-info/top_level.txt
npm_mcp-1.0.0.dist-info/RECORD
