Metadata-Version: 2.4
Name: npm-mcp
Version: 1.0.0
Summary: Production-ready MCP server for managing Nginx Proxy Manager instances via natural language
Author-email: Wade Woolwine <wade.woolwine@gmail.com>
License: MIT
Project-URL: Homepage, https://github.com/wadew/npm-mcp
Project-URL: Documentation, https://github.com/wadew/npm-mcp#documentation
Project-URL: Repository, https://github.com/wadew/npm-mcp.git
Project-URL: Issues, https://github.com/wadew/npm-mcp/issues
Project-URL: Changelog, https://github.com/wadew/npm-mcp/blob/main/CHANGELOG.md
Keywords: mcp,nginx,proxy,manager,llm,ai
Classifier: Development Status :: 5 - Production/Stable
Classifier: Intended Audience :: Developers
Classifier: Intended Audience :: System Administrators
Classifier: License :: OSI Approved :: MIT License
Classifier: Programming Language :: Python :: 3
Classifier: Programming Language :: Python :: 3.11
Classifier: Programming Language :: Python :: 3.12
Classifier: Programming Language :: Python :: 3.13
Classifier: Topic :: Software Development :: Libraries :: Python Modules
Classifier: Topic :: Internet :: Proxy Servers
Requires-Python: >=3.11
License-File: LICENSE
Requires-Dist: mcp>=1.25.0
Requires-Dist: httpx>=0.28.0
Requires-Dist: pydantic>=2.12.5
Requires-Dist: pyyaml>=6.0.3
Requires-Dist: cryptography>=46.0.3
Requires-Dist: keyring>=25.7.0
Requires-Dist: python-dotenv>=1.2.1
Requires-Dist: structlog>=25.5.0
Requires-Dist: tenacity>=9.1.2
Provides-Extra: dev
Requires-Dist: pytest>=9.0.2; extra == "dev"
Requires-Dist: pytest-asyncio>=1.3.0; extra == "dev"
Requires-Dist: pytest-cov>=7.0.0; extra == "dev"
Requires-Dist: pytest-mock>=3.15.0; extra == "dev"
Requires-Dist: pytest-httpx>=0.35.0; extra == "dev"
Requires-Dist: ruff>=0.14.11; extra == "dev"
Requires-Dist: mypy>=1.19.1; extra == "dev"
Requires-Dist: types-pyyaml>=6.0.12.20250915; extra == "dev"
Dynamic: license-file
